<people>
  <person>
    <id>1</id>
    <first_name>Dilly</first_name>
    <last_name>Bolstridge</last_name>
    <gender>Male</gender>
    <birth_date>9/27/2025</birth_date>
    <phone_number>773-216-5365</phone_number>
    <email>dbolstridge0@altervista.org</email>
  </person>
  <person>
    <id>2</id>
    <first_name>Saxon</first_name>
    <last_name>Bischop</last_name>
    <gender>Male</gender>
    <birth_date>9/5/2025</birth_date>
    <phone_number>745-531-7768</phone_number>
    <email>sbischop1@washington.edu</email>
  </person>
  <person>
    <id>3</id>
    <first_name>Moses</first_name>
    <last_name>Tremellan</last_name>
    <gender>Non-binary</gender>
    <birth_date>4/28/2025</birth_date>
    <phone_number>844-971-7314</phone_number>
    <email>mtremellan2@europa.eu</email>
  </person>
  <person>
    <id>4</id>
    <first_name>Merv</first_name>
    <last_name>Kintish</last_name>
    <gender>Male</gender>
    <birth_date>4/17/2025</birth_date>
    <phone_number>996-832-5472</phone_number>
    <email>mkintish3@4shared.com</email>
  </person>
  <person>
    <id>5</id>
    <first_name>Delphinia</first_name>
    <last_name>Limb</last_name>
    <gender>Female</gender>
    <birth_date>6/27/2025</birth_date>
    <phone_number>314-165-3598</phone_number>
    <email>dlimb4@amazonaws.com</email>
  </person>
  <person>
    <id>6</id>
    <first_name>Malissa</first_name>
    <last_name>Glandon</last_name>
    <gender>Female</gender>
    <birth_date>2/27/2025</birth_date>
    <phone_number>508-662-7873</phone_number>
    <email>mglandon5@fastcompany.com</email>
  </person>
  <person>
    <id>7</id>
    <first_name>Porty</first_name>
    <last_name>Dancer</last_name>
    <gender>Male</gender>
    <birth_date>5/17/2025</birth_date>
    <phone_number>412-314-9836</phone_number>
    <email>pdancer6@telegraph.co.uk</email>
  </person>
  <person>
    <id>8</id>
    <first_name>Lesya</first_name>
    <last_name>Croley</last_name>
    <gender>Female</gender>
    <birth_date>7/2/2025</birth_date>
    <phone_number>177-258-0925</phone_number>
    <email>lcroley7@smh.com.au</email>
  </person>
  <person>
    <id>9</id>
    <first_name>Torre</first_name>
    <last_name>Eastbrook</last_name>
    <gender>Male</gender>
    <birth_date>9/17/2025</birth_date>
    <phone_number>100-306-5349</phone_number>
    <email>teastbrook8@g.co</email>
  </person>
  <person>
    <id>10</id>
    <first_name>Vivyanne</first_name>
    <last_name>Oliphand</last_name>
    <gender>Bigender</gender>
    <birth_date>3/19/2025</birth_date>
    <phone_number>710-647-0441</phone_number>
    <email>voliphand9@delicious.com</email>
  </person>
</people>